murefi/__init__.py
murefi/core.py
murefi/datastructures.py
murefi/objectives.py
murefi/ode.py
murefi/symbolic.py
murefi/tests.py
murefi-5.3.0.dist-info/LICENSE
murefi-5.3.0.dist-info/METADATA
murefi-5.3.0.dist-info/WHEEL
murefi-5.3.0.dist-info/top_level.txt
murefi-5.3.0.dist-info/RECORD
