Metadata-Version: 2.1
Name: murefi
Version: 5.3.0
Summary: Package for multiple replicate fitting and Bayesian modeling.
Home-page: https://github.com/JuBiotech/murefi
Author: Laura Marie Helleckes, Michael Osthege
Author-email: l.helleckes@fz-juelich.de, m.osthege@fz-juelich.de
License: GNU Affero General Public License v3
Platform: UNKNOWN
Classifier: Programming Language :: Python
Classifier: Operating System :: OS Independent
Classifier: Programming Language :: Python :: 3.8
Classifier: Programming Language :: Python :: 3.9
Classifier: Programming Language :: Python :: 3.10
Classifier: License :: OSI Approved :: GNU Affero General Public License v3
Classifier: Intended Audience :: Science/Research
Classifier: Topic :: Scientific/Engineering
Classifier: Topic :: Scientific/Engineering :: Mathematics
License-File: LICENSE
Requires-Dist: calibr8 >=7.0.0
Requires-Dist: h5py
Requires-Dist: numpy
Requires-Dist: pandas
Requires-Dist: scipy
Requires-Dist: typing-extensions
